url_metadata/__init__.py
url_metadata/__main__.py
url_metadata/cache.py
url_metadata/core.py
url_metadata/exceptions.py
url_metadata/model.py
url_metadata/utils.py
url_metadata/sites/__init__.py
url_metadata/sites/abstract.py
url_metadata/sites/youtube/__init__.py
url_metadata/sites/youtube/yt_subs/__init__.py
url_metadata/sites/youtube/yt_subs/srt_converter.py
url_metadata/sites/youtube/yt_subs/subtitles_downloader.py
url_metadata-0.1.6.dist-info/LICENSE
url_metadata-0.1.6.dist-info/METADATA
url_metadata-0.1.6.dist-info/WHEEL
url_metadata-0.1.6.dist-info/entry_points.txt
url_metadata-0.1.6.dist-info/top_level.txt
url_metadata-0.1.6.dist-info/RECORD
