Metadata-Version: 2.1
Name: url-metadata
Version: 0.1.6
Summary: A cache which saves URL metadata and summarizes content
Home-page: https://github.com/seanbreckenridge/url_metadata
Author: Sean Breckenridge
Author-email: seanbrecke@gmail.com
License: http://www.apache.org/licenses/LICENSE-2.0
Keywords: url cache metadata youtube subtitles
Platform: UNKNOWN
Classifier: License :: OSI Approved :: Apache Software License
Classifier: Programming Language :: Python
Classifier: Programming Language :: Python :: 3
Classifier: Programming Language :: Python :: 3.7
Classifier: Programming Language :: Python :: 3.8
Requires-Dist: appdirs (>=1.4.4)
Requires-Dist: lassie (>=0.11.9)
Requires-Dist: readability-lxml (>=0.8.1)
Requires-Dist: backoff (>=1.10.0)
Requires-Dist: beautifulsoup4 (>=4.9.0)
Requires-Dist: click (>=7.1.2)
Requires-Dist: requests
Requires-Dist: logzero
Provides-Extra: testing
Requires-Dist: pytest ; extra == 'testing'
Requires-Dist: mypy ; extra == 'testing'
Requires-Dist: vcrpy ; extra == 'testing'
